{
  "operator": {
    "dashboard": {
      "title": "لوحة تحكم المشغل",
      "welcome": "مرحباً بعودتك",
      "overview": "نظرة عامة على المنصة",
      "monthlyRecurringRevenue": "الإيرادات الشهرية المتكررة",
      "annualRunRate": "معدل التشغيل السنوي (ARR)",
      "churnRate": "معدل التراجع (30 يوم)",
      "basedOnCurrentMRR": "بناءً على الإيرادات الشهرية الحالية",
      "schoolChurned": "مدرسة متراجعة",
      "schoolsChurned": "مدارس متراجعة",
      "viewAnalytics": "عرض التحليلات",
      "vsLastMonth": "مقارنة بالشهر الماضي",
      "activeSchools": "المدارس النشطة",
      "totalRevenue": "إجمالي الإيرادات",
      "growthRate": "معدل النمو",
      "platformHealth": "حالة المنصة",
      "systemStatus": "حالة النظام",
      "recentActivity": "النشاط الأخير",
      "quickActions": "إجراءات سريعة",
      "viewAllSchools": "عرض جميع المدارس",
      "manageBilling": "إدارة الفواتير",
      "viewReports": "عرض التقارير",
      "systemSettings": "إعدادات النظام"
    },
    "billing": {
      "title": "الفواتير",
      "overview": "نظرة عامة على الفواتير",
      "totalRevenue": "إجمالي الإيرادات",
      "fromPaidInvoices": "من {count} فاتورة مدفوعة",
      "paymentRate": "معدل الدفع",
      "ofInvoices": "{paid} من {total} فواتير",
      "openInvoices": "الفواتير المفتوحة",
      "awaitingPayment": "في انتظار الدفع",
      "pendingReceipts": "الإيصالات المعلقة",
      "awaitingReview": "في انتظار المراجعة",
      "noInvoices": "لا توجد فواتير",
      "invoicesWillAppear": "ستظهر الفواتير عند اكتمال دورات الفوترة.",
      "receipts": "الإيصالات",
      "receiptsDescription": "ستظهر إيصالات الدفع اليدوية هنا للمراجعة.",
      "uploadReceipt": "رفع إيصال",
      "approveReceipt": "الموافقة على الإيصال",
      "rejectReceipt": "رفض الإيصال",
      "receiptStatus": "حالة الإيصال",
      "pending": "معلق",
      "approved": "موافق عليه",
      "rejected": "مرفوض",
      "downloadInvoice": "تحميل الفاتورة",
      "viewInvoiceDetails": "عرض تفاصيل الفاتورة",
      "markAsPaid": "تحديد كمدفوع",
      "sendReminder": "إرسال تذكير",
      "billingHistory": "سجل الفواتير",
      "exportData": "تصدير البيانات"
    },
    "analytics": {
      "title": "التحليلات",
      "overview": "نظرة عامة على التحليلات",
      "performance": "مقاييس الأداء",
      "usage": "إحصائيات الاستخدام",
      "trends": "الاتجاهات",
      "reports": "التقارير",
      "customReports": "تقارير مخصصة",
      "exportReport": "تصدير التقرير",
      "dateRange": "نطاق التاريخ",
      "selectMetric": "اختر المقياس",
      "compareWith": "قارن مع",
      "previousPeriod": "الفترة السابقة",
      "customPeriod": "فترة مخصصة",
      "viewChart": "عرض الرسم البياني",
      "viewTable": "عرض الجدول",
      "downloadData": "تحميل البيانات"
    },
    "schools": {
      "title": "المدارس",
      "allSchools": "جميع المدارس",
      "activeSchools": "المدارس النشطة",
      "inactiveSchools": "المدارس غير النشطة",
      "draftSchools": "المدارس في المسودة",
      "schoolDetails": "تفاصيل المدرسة",
      "addSchool": "إضافة مدرسة",
      "editSchool": "تعديل المدرسة",
      "deleteSchool": "حذف المدرسة",
      "viewSchool": "عرض المدرسة",
      "schoolName": "اسم المدرسة",
      "schoolStatus": "حالة المدرسة",
      "subscriptionTier": "مستوى الاشتراك",
      "studentsCount": "عدد الطلاب",
      "teachersCount": "عدد المعلمين",
      "createdDate": "تاريخ الإنشاء",
      "lastActive": "آخر نشاط"
    },
    "common": {
      "actions": {
        "view": "عرض",
        "edit": "تعديل",
        "delete": "حذف",
        "add": "إضافة",
        "create": "إنشاء",
        "update": "تحديث",
        "submit": "إرسال",
        "cancel": "إلغاء",
        "save": "حفظ",
        "loading": "جاري التحميل...",
        "loadingInvoice": "جاري تحميل الفاتورة...",
        "viewAll": "عرض الكل",
        "addNew": "إضافة جديد",
        "quickActions": "إجراءات سريعة",
        "editDetails": "عدّل تفاصيل ملفك الشخصي هنا.",
        "viewAndManage": "عرض وإدارة العناصر",
        "createAndManage": "إنشاء وإدارة العناصر",
        "export": "تصدير",
        "import": "استيراد",
        "download": "تحميل",
        "upload": "رفع",
        "filter": "فلتر",
        "search": "بحث",
        "sort": "فرز",
        "refresh": "تحديث"
      },
      "status": {
        "active": "نشط",
        "inactive": "غير نشط",
        "pending": "معلق",
        "draft": "مسودة",
        "published": "منشور",
        "archived": "مؤرشف",
        "suspended": "معلق",
        "deleted": "محذوف"
      },
      "time": {
        "today": "اليوم",
        "yesterday": "أمس",
        "thisWeek": "هذا الأسبوع",
        "lastWeek": "الأسبوع الماضي",
        "thisMonth": "هذا الشهر",
        "lastMonth": "الشهر الماضي",
        "thisYear": "هذا العام",
        "lastYear": "العام الماضي",
        "custom": "مخصص",
        "from": "من",
        "to": "إلى"
      }
    }
  }
}
